ahab_py/__init__.py
ahab_py-1.0.0.data/scripts/createSlice.py
ahab_py-1.0.0.data/scripts/deleteSlice.py
ahab_py-1.0.0.data/scripts/getReservationStates.py
ahab_py-1.0.0.data/scripts/getReservationStitchInfo.py
ahab_py-1.0.0.data/scripts/getSliverProperties.py
ahab_py-1.0.0.data/scripts/getVersion.py
ahab_py-1.0.0.data/scripts/listMySlices.py
ahab_py-1.0.0.data/scripts/listResources.py
ahab_py-1.0.0.data/scripts/modifySlice.py
ahab_py-1.0.0.data/scripts/modifySliverGeneric.py
ahab_py-1.0.0.data/scripts/modifySliverSSH.py
ahab_py-1.0.0.data/scripts/performSliceStitch.py
ahab_py-1.0.0.data/scripts/permitSliceStitch.py
ahab_py-1.0.0.data/scripts/renewSlice.py
ahab_py-1.0.0.data/scripts/revokeSliceStitch.py
ahab_py-1.0.0.data/scripts/sliceStatus.py
ahab_py-1.0.0.data/scripts/undoSliceStitch.py
ahab_py-1.0.0.dist-info/LICENSE
ahab_py-1.0.0.dist-info/METADATA
ahab_py-1.0.0.dist-info/WHEEL
ahab_py-1.0.0.dist-info/top_level.txt
ahab_py-1.0.0.dist-info/RECORD
