Metadata-Version: 2.1
Name: ahab-py
Version: 1.0.0
Summary: AHAB package
Home-page: https://github.com/RENCI-NRIG/ahab
Author: RENCI
Author-email: kthare10@renci.org
License: UNKNOWN
Platform: UNKNOWN
Classifier: Programming Language :: Python :: 3 :: Only
Classifier: License :: OSI Approved :: MIT License
Classifier: Operating System :: OS Independent
Requires-Python: ~=3.6
